helloworld.py
helloworld_23487978234789-0.0.1.dist-info/LICENSE.txt
helloworld_23487978234789-0.0.1.dist-info/METADATA
helloworld_23487978234789-0.0.1.dist-info/WHEEL
helloworld_23487978234789-0.0.1.dist-info/top_level.txt
helloworld_23487978234789-0.0.1.dist-info/RECORD
