Metadata-Version: 2.1
Name: helloworld-23487978234789
Version: 0.0.1
Summary: Say Hello!
Home-page: https://github.com/ashutoshc8101/helloworld
Author: ashutoshc8101
Author-email: ashutoshc8101@gmail.com
License: UNKNOWN
Platform: UNKNOWN
Requires-Dist: blessings (~=1.7)
Provides-Extra: dev
Requires-Dist: pytest (>=3.7) ; extra == 'dev'
